Metadata-Version: 1.0
Name: pyramid-default-cors
Version: 0.2
Summary: Default wiring for CORS XHR
Home-page: https://github.com/emfloyd2/pyramid_default_cors
Author: Mark Floyd
Author-email: mark@goodrx.com
License: UNKNOWN
Keywords: config web wsgi pyramid
Platform: UNKNOWN
